flask_keycloak/__init__.py
flask_keycloak/core.py
flask_keycloak/examples/__init__.py
flask_keycloak/examples/dash_example.py
dash_keycloak-0.0.25.dist-info/METADATA
dash_keycloak-0.0.25.dist-info/WHEEL
dash_keycloak-0.0.25.dist-info/top_level.txt
dash_keycloak-0.0.25.dist-info/RECORD
