Metadata-Version: 2.1
Name: dash-keycloak
Version: 0.0.25
Summary: Flask extension providing Keycloak integration via the python-keycloak package
Home-page: https://github.com/thedirtyfew/dash-keycloak
Author: Emil Haldrup Eriksen
Author-email: emil.h.eriksen@gmail.com
License: MIT
Platform: UNKNOWN
Classifier: Programming Language :: Python :: 3
Requires-Dist: flask
Requires-Dist: python-keycloak
